pyautotem/__init__.py
pyautotem-0.0.2.dist-info/LICENSE.txt
pyautotem-0.0.2.dist-info/METADATA
pyautotem-0.0.2.dist-info/WHEEL
pyautotem-0.0.2.dist-info/top_level.txt
pyautotem-0.0.2.dist-info/RECORD
